<doctrine-mapping
    xmlns="http://doctrine-project.org/schemas/orm/doctrine-mapping"
    xmlns:xsi="http://www.w3.org/2001/XMLSchema-instance"
    xsi:schemaLocation="http://doctrine-project.org/schemas/orm/doctrine-mapping
        https://raw.github.com/doctrine/doctrine2/master/doctrine-mapping.xsd"
>

    <entity name="PhpIntegrator\Indexing\Structures\Structure" change-tracking-policy="DEFERRED_EXPLICIT">
        <id name="id" type="string"></id>

        <field name="name"               type="string"  nullable="false" length="255" />
        <field name="fqcn"               type="string"  nullable="false" length="255" />
        <field name="startLine"          type="integer" nullable="false" />
        <field name="endLine"            type="integer" nullable="false" />
        <field name="shortDescription"   type="text"    nullable="true"  length="15000" />
        <field name="longDescription"    type="text"    nullable="true"  length="15000" />
        <field name="isAbstract"         type="boolean" nullable="false" />
        <field name="isFinal"            type="boolean" nullable="false" />
        <field name="isAnnotation"       type="boolean" nullable="false" />
        <field name="isDeprecated"       type="boolean" nullable="false" />
        <field name="hasDocblock"        type="boolean" nullable="false" />

        <!-- These can't be join tables as the associations may not disappear if the other end is removed, otherwise -->
        <!-- we'd need to traverse the entire class list to update items when a missing structure is added. -->
        <field name="parentFqcns"        type="array"   nullable="false" />
        <field name="childFqcns"         type="array"   nullable="false" />
        <field name="interfaceFqcns"     type="array"   nullable="false" />
        <field name="implementorFqcns"   type="array"   nullable="false" />
        <field name="traitFqcns"         type="array"   nullable="false" />
        <field name="traitUserFqcns"     type="array"   nullable="false" />

        <many-to-one field="file" target-entity="PhpIntegrator\Indexing\Structures\File">
            <join-column on-delete="CASCADE" on-update="CASCADE" nullable="false" />

            <cache>
                <usage>READ_ONLY</usage>
                <region>structureFile</region>
            </cache>
        </many-to-one>

        <many-to-one field="type" target-entity="PhpIntegrator\Indexing\Structures\StructureType">
            <join-column on-delete="RESTRICT" on-update="RESTRICT" nullable="false" />

            <cache>
                <usage>READ_ONLY</usage>
                <region>structureType</region>
            </cache>
        </many-to-one>

        <one-to-many field="traitAliases" target-entity="PhpIntegrator\Indexing\Structures\StructureTraitAlias" mapped-by="structure">
            <cache>
                <usage>READ_ONLY</usage>
                <region>structureTraitAliases</region>
            </cache>
        </one-to-many>

        <one-to-many field="traitPrecedences" target-entity="PhpIntegrator\Indexing\Structures\StructureTraitPrecedence" mapped-by="structure">
            <cache>
                <usage>READ_ONLY</usage>
                <region>structureTraitPrecedences</region>
            </cache>
        </one-to-many>

        <one-to-many field="constants" target-entity="PhpIntegrator\Indexing\Structures\Constant" mapped-by="structure">
            <cache>
                <usage>READ_ONLY</usage>
                <region>structureConstants</region>
            </cache>
        </one-to-many>

        <one-to-many field="properties" target-entity="PhpIntegrator\Indexing\Structures\Property" mapped-by="structure">
            <cache>
                <usage>READ_ONLY</usage>
                <region>structureProperties</region>
            </cache>
        </one-to-many>

        <one-to-many field="methods" target-entity="PhpIntegrator\Indexing\Structures\Function_" mapped-by="structure">
            <cache>
                <usage>READ_ONLY</usage>
                <region>structureMethods</region>
            </cache>
        </one-to-many>

        <cache>
            <usage>READ_ONLY</usage>
            <region>structure</region>
        </cache>
    </entity>

</doctrine-mapping>
